MinutiaeClassificator
