Metadata-Version: 2.1
Name: MinutiaeClassificator
Version: 1.0.0
Summary: Minutiae extraction and classification tool
Home-page: https://github.com/jakubarendac/MinutiaeClassificator
Author: Jakub Arendac
Author-email: jakub.arendac105@gmail.com
License: MIT
Download-URL: https://github.com/jakubarendac/MinutiaeClassificator/archive/1.0.0.tar.gz
Keywords: minutiae,extraction,classification,biometrics
Platform: UNKNOWN
Classifier: Development Status :: 3 - Alpha
Classifier: Intended Audience :: Developers
Classifier: Topic :: Scientific/Engineering :: Image Recognition
Classifier: License :: OSI Approved :: MIT License
Classifier: Programming Language :: Python :: 2.7
